iotbr/__init__.py
iotbr/deflate.py
iotbr/io_system.py
iotbr/tru.py
iotbr/tru_pb.py
iotbr/IBGE/dictionary_1.csv
iotbr/IBGE/nivel_12_2000_2020_xls/12_tab1_2000.xls
iotbr/IBGE/nivel_12_2000_2020_xls/12_tab1_2001.xls
iotbr/IBGE/nivel_12_2000_2020_xls/12_tab1_2002.xls
iotbr/IBGE/nivel_12_2000_2020_xls/12_tab1_2003.xls
iotbr/IBGE/nivel_12_2000_2020_xls/12_tab1_2004.xls
iotbr/IBGE/nivel_12_2000_2020_xls/12_tab1_2005.xls
iotbr/IBGE/nivel_12_2000_2020_xls/12_tab1_2006.xls
iotbr/IBGE/nivel_12_2000_2020_xls/12_tab1_2007.xls
iotbr/IBGE/nivel_12_2000_2020_xls/12_tab1_2008.xls
iotbr/IBGE/nivel_12_2000_2020_xls/12_tab1_2009.xls
iotbr/IBGE/nivel_12_2000_2020_xls/12_tab1_2010.xls
iotbr/IBGE/nivel_12_2000_2020_xls/12_tab1_2011.xls
iotbr/IBGE/nivel_12_2000_2020_xls/12_tab1_2012.xls
iotbr/IBGE/nivel_12_2000_2020_xls/12_tab1_2013.xls
iotbr/IBGE/nivel_12_2000_2020_xls/12_tab1_2014.xls
iotbr/IBGE/nivel_12_2000_2020_xls/12_tab1_2015.xls
iotbr/IBGE/nivel_12_2000_2020_xls/12_tab1_2016.xls
iotbr/IBGE/nivel_12_2000_2020_xls/12_tab1_2017.xls
iotbr/IBGE/nivel_12_2000_2020_xls/12_tab1_2018.xls
iotbr/IBGE/nivel_12_2000_2020_xls/12_tab1_2019.xls
iotbr/IBGE/nivel_12_2000_2020_xls/12_tab1_2020.xls
iotbr/IBGE/nivel_12_2000_2020_xls/12_tab2_2000.xls
iotbr/IBGE/nivel_12_2000_2020_xls/12_tab2_2001.xls
iotbr/IBGE/nivel_12_2000_2020_xls/12_tab2_2002.xls
iotbr/IBGE/nivel_12_2000_2020_xls/12_tab2_2003.xls
iotbr/IBGE/nivel_12_2000_2020_xls/12_tab2_2004.xls
iotbr/IBGE/nivel_12_2000_2020_xls/12_tab2_2005.xls
iotbr/IBGE/nivel_12_2000_2020_xls/12_tab2_2006.xls
iotbr/IBGE/nivel_12_2000_2020_xls/12_tab2_2007.xls
iotbr/IBGE/nivel_12_2000_2020_xls/12_tab2_2008.xls
iotbr/IBGE/nivel_12_2000_2020_xls/12_tab2_2009.xls
iotbr/IBGE/nivel_12_2000_2020_xls/12_tab2_2010.xls
iotbr/IBGE/nivel_12_2000_2020_xls/12_tab2_2011.xls
iotbr/IBGE/nivel_12_2000_2020_xls/12_tab2_2012.xls
iotbr/IBGE/nivel_12_2000_2020_xls/12_tab2_2013.xls
iotbr/IBGE/nivel_12_2000_2020_xls/12_tab2_2014.xls
iotbr/IBGE/nivel_12_2000_2020_xls/12_tab2_2015.xls
iotbr-0.0.19.dist-info/LICENSE
iotbr-0.0.19.dist-info/METADATA
iotbr-0.0.19.dist-info/WHEEL
iotbr-0.0.19.dist-info/top_level.txt
iotbr-0.0.19.dist-info/RECORD
