Metadata-Version: 2.1
Name: iotbr
Version: 0.0.19
Summary: Import data from Table of Input-Output from IBGE
Home-page: https://github.com/fms-1988
Author: Felipe Morelli Da Silva
Author-email: fms.morelli@gmail.com
Classifier: Programming Language :: Python :: 3
Classifier: License :: OSI Approved :: MIT License
Classifier: Operating System :: OS Independent
Requires-Python: >=3.7
License-File: LICENSE
Requires-Dist: xlrd
